svk/__init__.py
svk-0.0.1.dist-info/LICENSE.txt
svk-0.0.1.dist-info/METADATA
svk-0.0.1.dist-info/WHEEL
svk-0.0.1.dist-info/top_level.txt
svk-0.0.1.dist-info/RECORD
